{"cameraMode":{"drawMode":0,"name":"Shaded","section":"Shading Mode"},"sceneLighting":true,"audioPlay":false,"sceneViewState":{"showFog":true,"showMaterialUpdate":false,"showSkybox":true,"showFlares":true,"showImageEffects":true,"showParticleSystems":true},"in2DMode":false,"pivot":{"x":-207.37738037109376,"y":-24.464706420898439,"z":358.28619384765627},"rotation":{"x":0.04647974669933319,"y":-0.011987220495939255,"z":0.0005518086836673319,"w":0.99885493516922},"size":177.93447875976563,"orthographic":false}